bengal/__init__.py
bengal/__main__.py
bengal/py.typed
bengal/analysis/__init__.py
bengal/analysis/community_detection.py
bengal/analysis/graph_analysis.py
bengal/analysis/graph_reporting.py
bengal/analysis/graph_visualizer.py
bengal/analysis/knowledge_graph.py
bengal/analysis/link_suggestions.py
bengal/analysis/link_types.py
bengal/analysis/page_rank.py
bengal/analysis/path_analysis.py
bengal/analysis/performance_advisor.py
bengal/analysis/results.py
bengal/assets/__init__.py
bengal/assets/manifest.py
bengal/assets/pipeline.py
bengal/autodoc/__init__.py
bengal/autodoc/base.py
bengal/autodoc/config.py
bengal/autodoc/docstring_parser.py
bengal/autodoc/utils.py
bengal/autodoc/extractors/__init__.py
bengal/autodoc/extractors/cli.py
bengal/autodoc/extractors/openapi.py
bengal/autodoc/extractors/python/__init__.py
bengal/autodoc/extractors/python/aliases.py
bengal/autodoc/extractors/python/extractor.py
bengal/autodoc/extractors/python/inheritance.py
bengal/autodoc/extractors/python/module_info.py
bengal/autodoc/extractors/python/signature.py
bengal/autodoc/extractors/python/skip_logic.py
bengal/autodoc/models/__init__.py
bengal/autodoc/models/cli.py
bengal/autodoc/models/common.py
bengal/autodoc/models/openapi.py
bengal/autodoc/models/python.py
bengal/autodoc/orchestration/__init__.py
bengal/autodoc/orchestration/extractors.py
bengal/autodoc/orchestration/index_pages.py
bengal/autodoc/orchestration/orchestrator.py
bengal/autodoc/orchestration/page_builders.py
bengal/autodoc/orchestration/result.py
bengal/autodoc/orchestration/section_builders.py
bengal/autodoc/orchestration/template_env.py
bengal/autodoc/orchestration/utils.py
bengal/cache/__init__.py
bengal/cache/asset_dependency_map.py
bengal/cache/cache_store.py
bengal/cache/cacheable.py
bengal/cache/compression.py
bengal/cache/dependency_tracker.py
bengal/cache/page_discovery_cache.py
bengal/cache/paths.py
bengal/cache/query_index.py
bengal/cache/query_index_registry.py
bengal/cache/taxonomy_index.py
bengal-0.1.5.dist-info/licenses/LICENSE
bengal-0.1.5.dist-info/METADATA
bengal-0.1.5.dist-info/WHEEL
bengal-0.1.5.dist-info/entry_points.txt
bengal-0.1.5.dist-info/top_level.txt
bengal-0.1.5.dist-info/RECORD
