Metadata-Version: 2.4
Name: bengal
Version: 0.1.5
Summary: A high-performance static site generator with modular architecture
Author-email: Bengal Contributors <lbeeze@icloud.com>
License-Expression: MIT
Project-URL: Homepage, https://github.com/lbliii/bengal
Project-URL: Documentation, https://github.com/lbliii/bengal
Project-URL: Repository, https://github.com/lbliii/bengal
Project-URL: Bug Tracker, https://github.com/lbliii/bengal/issues
Keywords: static-site-generator,ssg,documentation,markdown,website,free-threading,performance
Classifier: Development Status :: 3 - Alpha
Classifier: Intended Audience :: Developers
Classifier: Programming Language :: Python :: 3
Classifier: Programming Language :: Python :: 3.14
Classifier: Topic :: Documentation
Classifier: Topic :: Software Development :: Documentation
Requires-Python: >=3.14
License-File: LICENSE
Requires-Dist: click>=8.1.7
Requires-Dist: mistune>=3.0.0
Requires-Dist: jinja2>=3.1.0
Requires-Dist: pyyaml>=6.0
Requires-Dist: pygments>=2.18.0
Requires-Dist: python-frontmatter>=1.0.0
Requires-Dist: jsmin>=3.0.1
Requires-Dist: pillow>=10.0.0
Requires-Dist: psutil>=5.9.0
Requires-Dist: textual>=0.89
Requires-Dist: textual-serve>=0.1.0
Requires-Dist: questionary>=2.0.0
Requires-Dist: watchfiles>=0.20
Requires-Dist: httpx>=0.27.0
Requires-Dist: uvloop>=0.21.0; sys_platform != "win32"
Provides-Extra: search
Requires-Dist: lunr>=0.7.0; extra == "search"
Provides-Extra: github
Requires-Dist: aiohttp>=3.9.0; extra == "github"
Provides-Extra: notion
Requires-Dist: aiohttp>=3.9.0; extra == "notion"
Provides-Extra: rest
Requires-Dist: aiohttp>=3.9.0; extra == "rest"
Provides-Extra: all-sources
Requires-Dist: aiohttp>=3.9.0; extra == "all-sources"
Dynamic: license-file
